custom_package_25731542/__init__.py
custom_package_25731542/data_processing.py
custom_package_25731542/eda.py
custom_package_25731542/feature_analysis.py
custom_package_25731542/feature_engineering.py
custom_package_25731542/model_helpers.py
custom_package_25731542-0.1.3.dist-info/METADATA
custom_package_25731542-0.1.3.dist-info/WHEEL
custom_package_25731542-0.1.3.dist-info/RECORD
