Metadata-Version: 2.4
Name: custom_package_25731542
Version: 0.1.3
Summary: Custom package for EDA and filling missing values
Author: Rohan Chaudhary
Author-email: Rohan.chaudhary@student.uts.edu.au
Requires-Python: >=3.12,<4.0
Classifier: Programming Language :: Python :: 3
Classifier: Programming Language :: Python :: 3.12
Classifier: Programming Language :: Python :: 3.13
Classifier: Programming Language :: Python :: 3.14
Requires-Dist: pandas (>=2.2.2,<3.0.0)
